model_opt/__init__.py
model_opt/cli.py
model_opt/adapters/base.py
model_opt/adapters/jax.py
model_opt/adapters/keras.py
model_opt/adapters/onnx.py
model_opt/adapters/tensorflow.py
model_opt/adapters/torch.py
model_opt/agent/README.md
model_opt/agent/__init__.py
model_opt/agent/analyzer_agent.py
model_opt/agent/tools/__init__.py
model_opt/agent/tools/analyzer.py
model_opt/agent/tools/research/__init__.py
model_opt/agent/tools/research/arxiv_crawler.py
model_opt/agent/tools/research/huggingface.py
model_opt/agent/tools/research/metadata_extractor.py
model_opt/agent/tools/research/paper_filter.py
model_opt/agent/tools/research/parallel_crawler.py
model_opt/agent/tools/research/scheduler.py
model_opt/agent/tools/research/semantic_scholar.py
model_opt/autotuner/README.md
model_opt/autotuner/__init__.py
model_opt/autotuner/intelligent_optimizer.py
model_opt/autotuner/search_space.py
model_opt/autotuner/tree_search.py
model_opt/core/__init__.py
model_opt/core/cli_engine.py
model_opt/core/config.py
model_opt/core/environment.py
model_opt/core/exceptions.py
model_opt/core/hardware.py
model_opt/core/logger.py
model_opt/core/model_loader.py
model_opt/core/model_zoo.py
model_opt/core/optimizer.py
model_opt/core/storage/__init__.py
model_opt/core/storage/base.py
model_opt/core/storage/chromadb_backend.py
model_opt/core/storage/mongodb_backend.py
model_opt/core/storage/neo4j_backend.py
model_opt/core/storage/redis_backend.py
model_opt/evaluation/__init__.py
model_opt/evaluation/benchmark.py
model_opt/evaluation/datasets.py
model_opt/evaluation/metrics.py
model_opt/pipelines/compose.py
model_opt/techniques/README.md
model_opt/techniques/__init__.py
model_opt/techniques/decompose.py
model_opt/techniques/fuse.py
model_opt/techniques/prune.py
model_opt/techniques/quantize.py
model_opt/techniques/decomposition/__init__.py
model_opt/techniques/decomposition/decomposition_svd.py
model_opt/techniques/fusion/__init__.py
model_opt/techniques/fusion/fusion_conv_bn_relu.py
model_opt-0.1.1.dist-info/licenses/LICENSE
model_opt-0.1.1.dist-info/METADATA
model_opt-0.1.1.dist-info/WHEEL
model_opt-0.1.1.dist-info/entry_points.txt
model_opt-0.1.1.dist-info/top_level.txt
model_opt-0.1.1.dist-info/RECORD
