Metadata-Version: 2.4
Name: model-opt
Version: 0.1.1
Summary: Model optimization toolkit with agentic experimentation and intelligent workflow planning
Author: Model Opt Contributors
License: MIT
Keywords: machine-learning,model-optimization,quantization,pruning,compression
Classifier: Development Status :: 3 - Alpha
Classifier: Intended Audience :: Developers
Classifier: Intended Audience :: Science/Research
Classifier: License :: OSI Approved :: MIT License
Classifier: Programming Language :: Python :: 3
Classifier: Programming Language :: Python :: 3.11
Classifier: Topic :: Scientific/Engineering :: Artificial Intelligence
Requires-Python: >=3.11
License-File: LICENSE
Requires-Dist: numpy>=1.21.0
Requires-Dist: requests>=2.31.0
Requires-Dist: pyyaml>=6.0
Provides-Extra: pytorch
Requires-Dist: torch>=2.1.0; extra == "pytorch"
Requires-Dist: torchvision>=0.16.0; extra == "pytorch"
Requires-Dist: torchao>=0.1.0; extra == "pytorch"
Requires-Dist: torch-pruning>=1.3.0; extra == "pytorch"
Requires-Dist: tomesd; extra == "pytorch"
Requires-Dist: timm>=0.9.0; extra == "pytorch"
Requires-Dist: ultralytics>=8.0.0; extra == "pytorch"
Provides-Extra: tensorflow
Requires-Dist: tensorflow>=2.13.0; extra == "tensorflow"
Provides-Extra: optimization
Requires-Dist: nncf; extra == "optimization"
Requires-Dist: neural-compressor; extra == "optimization"
Provides-Extra: tree-search
Requires-Dist: networkx>=3.1; extra == "tree-search"
Provides-Extra: databases
Requires-Dist: pymongo>=4.0; extra == "databases"
Requires-Dist: redis>=5.0; extra == "databases"
Requires-Dist: neo4j; extra == "databases"
Requires-Dist: chromadb>=0.4.0; extra == "databases"
Provides-Extra: research
Requires-Dist: aiohttp>=3.9.0; extra == "research"
Requires-Dist: arxiv>=2.1.0; extra == "research"
Requires-Dist: sentence-transformers>=2.2.0; extra == "research"
Requires-Dist: faiss-cpu; extra == "research"
Provides-Extra: federated
Requires-Dist: pymongo>=4.0; extra == "federated"
Requires-Dist: redis>=5.0; extra == "federated"
Requires-Dist: neo4j>=5.0; extra == "federated"
Requires-Dist: networkx>=3.1; extra == "federated"
Requires-Dist: numpy>=1.21; extra == "federated"
Requires-Dist: scipy>=1.9; extra == "federated"
Requires-Dist: httpx>=0.24.0; extra == "federated"
Provides-Extra: evaluation
Requires-Dist: pycocotools; extra == "evaluation"
Requires-Dist: opencv-python; extra == "evaluation"
Provides-Extra: llm
Requires-Dist: openai; extra == "llm"
Requires-Dist: google-generativeai; extra == "llm"
Requires-Dist: together; extra == "llm"
Requires-Dist: vllm>=0.6.0; extra == "llm"
Requires-Dist: uvloop>=0.19.0; platform_system != "Windows" and extra == "llm"
Provides-Extra: dev
Requires-Dist: torch>=2.1.0; extra == "dev"
Requires-Dist: torchvision>=0.16.0; extra == "dev"
Requires-Dist: torchao>=0.1.0; extra == "dev"
Requires-Dist: torch-pruning>=1.3.0; extra == "dev"
Requires-Dist: networkx>=3.1; extra == "dev"
Provides-Extra: all
Requires-Dist: torch>=2.1.0; extra == "all"
Requires-Dist: torchvision>=0.16.0; extra == "all"
Requires-Dist: torchao>=0.1.0; extra == "all"
Requires-Dist: torch-pruning>=1.3.0; extra == "all"
Requires-Dist: tomesd; extra == "all"
Requires-Dist: timm>=0.9.0; extra == "all"
Requires-Dist: ultralytics>=8.0.0; extra == "all"
Requires-Dist: tensorflow>=2.13.0; extra == "all"
Requires-Dist: nncf; extra == "all"
Requires-Dist: neural-compressor; extra == "all"
Requires-Dist: networkx>=3.1; extra == "all"
Requires-Dist: pymongo>=4.0; extra == "all"
Requires-Dist: redis>=5.0; extra == "all"
Requires-Dist: neo4j; extra == "all"
Requires-Dist: chromadb>=0.4.0; extra == "all"
Requires-Dist: aiohttp>=3.9.0; extra == "all"
Requires-Dist: arxiv>=2.1.0; extra == "all"
Requires-Dist: requests>=2.31.0; extra == "all"
Requires-Dist: tqdm; extra == "all"
Requires-Dist: Pillow; extra == "all"
Requires-Dist: scikit-image; extra == "all"
Requires-Dist: scikit-learn; extra == "all"
Requires-Dist: tensorboard; extra == "all"
Requires-Dist: matplotlib<3.10.0; extra == "all"
Requires-Dist: scipy; extra == "all"
Requires-Dist: protobuf; extra == "all"
Requires-Dist: pydantic<2.12.0,>=2.0; extra == "all"
Requires-Dist: sentence-transformers>=2.2.0; extra == "all"
Requires-Dist: faiss-cpu; extra == "all"
Requires-Dist: openai; extra == "all"
Requires-Dist: google-generativeai; extra == "all"
Requires-Dist: together; extra == "all"
Requires-Dist: onnx>=1.14.0; extra == "all"
Requires-Dist: onnxruntime>=1.16.0; extra == "all"
Requires-Dist: pycocotools; extra == "all"
Requires-Dist: opencv-python; extra == "all"
Requires-Dist: vllm>=0.6.0; extra == "all"
Requires-Dist: uvloop>=0.19.0; platform_system != "Windows" and extra == "all"
Requires-Dist: httpx>=0.24.0; extra == "all"
Dynamic: license-file
